MaxEmbeds.py
maxembeds-0.0.1.dist-info/METADATA
maxembeds-0.0.1.dist-info/WHEEL
maxembeds-0.0.1.dist-info/top_level.txt
maxembeds-0.0.1.dist-info/RECORD
