Metadata-Version: 2.1
Name: maxembeds
Version: 0.0.1
Summary: Awesome EmbedBuilder for discord.py
Home-page: UNKNOWN
Author: UNKNOWN
Author-email: UNKNOWN
License: UNKNOWN
Platform: UNKNOWN
